esa_local_llm/__init__.py
esa_local_llm-0.0.15.dist-info/LICENSE
esa_local_llm-0.0.15.dist-info/METADATA
esa_local_llm-0.0.15.dist-info/WHEEL
esa_local_llm-0.0.15.dist-info/top_level.txt
esa_local_llm-0.0.15.dist-info/RECORD
