Metadata-Version: 2.1
Name: esa-local-llm
Version: 0.0.15
Summary: ESA Local-LLM is a llama.cpp server in Docker with OpenAI Style Endpoints.
Author: Michael Cloutier
Author-email: michael.cloutier@experian.com
Requires-Python: >=3.10
License-File: LICENSE
Requires-Dist: fastapi
Requires-Dist: pydantic
Requires-Dist: requests
Requires-Dist: uvicorn
Requires-Dist: pyjwt
Requires-Dist: tiktoken
Requires-Dist: llama-cpp-python ==0.2.11
Requires-Dist: python-dotenv
Requires-Dist: GPUtil
Requires-Dist: psutil
Requires-Dist: beautifulsoup4
